setup.cfg
setup.py
elb_update_security_policy/UpdateSecurityPolicy.py
elb_update_security_policy/__init__.py
elb_update_security_policy/cli.py
elb_update_security_policy/util.py
elb_update_security_policy.egg-info/PKG-INFO
elb_update_security_policy.egg-info/SOURCES.txt
elb_update_security_policy.egg-info/dependency_links.txt
elb_update_security_policy.egg-info/entry_points.txt
elb_update_security_policy.egg-info/requires.txt
elb_update_security_policy.egg-info/top_level.txt