Metadata-Version: 1.1
Name: elb-update-security-policy
Version: 0.0.2
Summary: ELB Security Policy Update Tool
Home-page: https://github.com/WrathOfChris/elb-update-security-policy
Author: Chris Maxwell
Author-email: chris@wrathofchris.com
License: Apache
Download-URL: https://github.com/WrathOfChris/elb-update-security-policy/tarball/0.0.2
Platform: UNKNOWN
